CHANGELOG.md
clone_all_from_org/__init__.py
clone_all_from_org/clone_all_from_org.py
clone_all_from_org/main.py
clone_all_from_org/py.typed
justfile
noxfile.py
clone_all_from_org-0.2.2.dist-info/entry_points.txt
clone_all_from_org-0.2.2.dist-info/LICENSE
clone_all_from_org-0.2.2.dist-info/WHEEL
clone_all_from_org-0.2.2.dist-info/METADATA
clone_all_from_org-0.2.2.dist-info/RECORD
