Metadata-Version: 2.1
Name: clone-all-from-org
Version: 0.2.2
Summary: CLI tool to clone all repos from a given organization or user
Home-page: https://github.com/micktwomey/clone-all-from-org
License: MIT
Author: Michael Twomey
Author-email: mick@twomeylee.name
Requires-Python: >=3.9,<4.0
Classifier: License :: OSI Approved :: MIT License
Classifier: Programming Language :: Python :: 3
Classifier: Programming Language :: Python :: 3.10
Classifier: Programming Language :: Python :: 3.9
Requires-Dist: PyYAML (>=6.0,<7.0)
Requires-Dist: aioitertools (>=0.10.0,<0.11.0)
Requires-Dist: click (>=8.1,<9.0)
Requires-Dist: clone-repo (>=0.2.0,<1.0.0)
Requires-Dist: gidgethub (>=5.1,<6.0)
Requires-Dist: httpx (>=0.22,<0.23)
Requires-Dist: pydantic (>=1.9,<2.0)
Requires-Dist: rich (>=12.0,<13.0)
Requires-Dist: structlog (>=21.5,<22.0)
Requires-Dist: typer (>=0.4,<0.5)
Requires-Dist: types-PyYAML (>=6.0,<7.0)
Project-URL: Repository, https://github.com/micktwomey/clone-all-from-org
